<?xml version="1.0" encoding="UTF-8"?>
<flow xmlns="http://www.springframework.org/schema/webflow"
	xmlns:xsi="http://www.w3.org/2001/XMLSchema-instance"
	xsi:schemaLocation="http://www.springframework.org/schema/webflow
							http://www.springframework.org/schema/webflow/spring-webflow.xsd">

<on-start>
    <evaluate expression="new com.hrms.domain.Employee()" result="flowScope.employee" />
    <evaluate expression="new com.hrms.webflow.FileUploadHandler()" result="flowScope.fileUploadHandler" />
</on-start>

<view-state id="employeeForm" model="employee">
    <transition on="photo" to="employeePhoto"/>
    <transition on="cancel" to="cancelRegistration"/>
</view-state>

<view-state id="employeePhoto" model="fileUploadHandler">
    <transition on="contacts" to="employeeContactsForm">
    	<evaluate expression="fileUploadHandler.getImage()" result="employee.photo"></evaluate>
    </transition>
    <transition on="back" to="employeeForm"/>
</view-state>

<view-state id="employeeContactsForm" model="employee">
    <transition on="save" to="saveEmployee"/>
    <transition on="back" to="employeePhoto"/>
</view-state>
 
<action-state id="saveEmployee">
	<evaluate expression="addEmployeeControllerHelper.saveEmployee(employee)" result="employee"/>
	<transition to="employeeInfo" />
</action-state>

<view-state id="employeeInfo" model="employee">
	<transition on="home" to="cancelRegistration"/>
</view-state>

<end-state id="cancelRegistration" view="externalRedirect:contextRelative:/"/>

</flow>
